{
  "miniprogramRoot": "dist/",
  "projectname": "Labwant",
  "description": "Labwant",
  "appid": "wxfb6f19dea1c73480",
  "setting": {
    "urlCheck": true,
    "es6": true,
    "enhance": true,
    "compileHotReLoad": false,
    "postcss": false,
    "minified": true,
    "babelSetting": {
      "ignore": [],
      "disablePlugins": [],
      "outputPath": ""
    }
  },
  "compileType": "miniprogram",
  "libVersion": "3.8.8",
  "srcMiniprogramRoot": "dist/",
  "packOptions": {
    "ignore": [],
    "include": []
  },
  "condition": {},
  "editorSetting": {
    "tabIndent": "auto",
    "tabSize": 2
  }
}